pypublicwww/__init__.py
pypublicwww/lib.py
pypublicwww/pypublicwww.py
pypublicwww-0.0.8.data/scripts/publicwww
pypublicwww-0.0.8.dist-info/AUTHORS
pypublicwww-0.0.8.dist-info/LICENSE
pypublicwww-0.0.8.dist-info/METADATA
pypublicwww-0.0.8.dist-info/WHEEL
pypublicwww-0.0.8.dist-info/top_level.txt
pypublicwww-0.0.8.dist-info/RECORD
